autosnapgene/__init__.py
autosnapgene/api.py
autosnapgene/cli.py
autosnapgene/errors.py
autosnapgene/parser.py
autosnapgene/util.py
autosnapgene/.pytest_cache/.gitignore
autosnapgene/.pytest_cache/CACHEDIR.TAG
autosnapgene/.pytest_cache/README.md
autosnapgene/.pytest_cache/v/cache/nodeids
autosnapgene/.pytest_cache/v/cache/stepwise
autosnapgene/blocks/__init__.py
autosnapgene/blocks/alignments.py
autosnapgene/blocks/enzymes.py
autosnapgene/blocks/features.py
autosnapgene/blocks/header.py
autosnapgene/blocks/history.py
autosnapgene/blocks/misc.py
autosnapgene/blocks/notes.py
autosnapgene/blocks/primers.py
autosnapgene/blocks/sequences.py
autosnapgene-0.2.0.dist-info/entry_points.txt
autosnapgene-0.2.0.dist-info/licenses/LICENSE.txt
autosnapgene-0.2.0.dist-info/WHEEL
autosnapgene-0.2.0.dist-info/METADATA
autosnapgene-0.2.0.dist-info/RECORD
