Metadata-Version: 2.4
Name: autosnapgene
Version: 0.2.0
Summary: Provide an API for parsing SnapGene *.dna files.
Author-email: Kale Kundert <kale@thekunderts.net>
Requires-Python: ~=3.7
License-File: LICENSE.txt
Requires-Dist: docopt
Requires-Dist: arrow
Requires-Dist: autoprop
Requires-Dist: nonstdlib
Requires-Dist: more_itertools
Project-URL: Version Control, https://github.com/kalekundert/autosnapgene
